mihawk/__init__.py
mihawk/_utils.py
mihawk/cli.py
mihawk/graphs.py
mihawk/models.py
mihawk/readers.py
mihawk/static/agios_athanasios.kml
mihawk/static/agios_gewrgios.kml
mihawk/static/agios_iwannhs.kml
mihawk/static/agios_loukas.kml
mihawk/static/depos.kml
mihawk/static/kentro_meshmeri.kml
mihawk/static/kentro_nyxta.kml
mihawk/static/komnhnwn.kml
mihawk/static/panagia_kentro.kml
mihawk/static/panagia_profhths_hlias.kml
mihawk/static/vyrwnas.kml
mihawk-0.1.0.dist-info/LICENSE
mihawk-0.1.0.dist-info/METADATA
mihawk-0.1.0.dist-info/WHEEL
mihawk-0.1.0.dist-info/entry_points.txt
mihawk-0.1.0.dist-info/RECORD
